LICENSE.txt
MANIFEST.in
README.md
setup.cfg
setup.py
jurt/__init__.py
jurt/__main__.py
jurt/core.py
jurt/reg.py
jurt/t1.py
jurt.egg-info/PKG-INFO
jurt.egg-info/SOURCES.txt
jurt.egg-info/dependency_links.txt
jurt.egg-info/entry_points.txt
jurt.egg-info/top_level.txt
test/__init__.py
test/__main__.py
test/test_jurt.py