Metadata-Version: 2.1
Name: jurt
Version: 1.0.1
Summary: Jeff's Unified Registration Tool
Home-page: https://github.com/jme2041/jurt
Author: Jeffrey M. Engelmann
Author-email: jme2041@icloud.com
Maintainer: Jeffrey M. Engelmann
Maintainer-email: jme2041@icloud.com
License: BSD 3-Clause License
Keywords: mri fmri analysis preprocessing registration normalization
Platform: UNKNOWN
Classifier: Development Status :: 2 - Pre-Alpha
Classifier: License :: OSI Approved :: BSD License
Classifier: Programming Language :: Python :: 3.7
Classifier: Programming Language :: Python :: Implementation :: CPython
Classifier: Operating System :: MacOS :: MacOS X
Classifier: Operating System :: POSIX :: Linux
Classifier: Environment :: Console
Classifier: Natural Language :: English
Classifier: Intended Audience :: Science/Research
Classifier: Topic :: Scientific/Engineering :: Bio-Informatics
Requires-Python: >=3.6
